pysparker/__init__.py
pysparker/utils.py
pysparker-0.1.1.dist-info/WHEEL
pysparker-0.1.1.dist-info/METADATA
pysparker-0.1.1.dist-info/RECORD
