Metadata-Version: 2.1
Name: pysparker
Version: 0.1.1
Summary: Some utility functions for PySpark.
Author: Ben Du
Author-email: longendu@yahoo.com
Requires-Python: >=3.7.1,<3.11
Classifier: Programming Language :: Python :: 3
Classifier: Programming Language :: Python :: 3.10
Classifier: Programming Language :: Python :: 3.8
Classifier: Programming Language :: Python :: 3.9
Requires-Dist: datacompy (>=0.8.1)
Requires-Dist: loguru (>=0.6.0)
